Compiled from "Math.java"
class com.czw.basic.Jvm.Math {
  public static final java.lang.Integer CONSTANT_1;

  com.czw.basic.Jvm.Math();
    Code:
       0: aload_0
       1: invokespecial #1                  // Method java/lang/Object."<init>":()V
       4: return

  public static void main(java.lang.String[]);
    Code:
       0: new           #2                  // class com/czw/basic/Jvm/Math
       3: dup
       4: invokespecial #3                  // Method "<init>":()V
       7: astore_1
       8: getstatic     #4                  // Field java/lang/System.out:Ljava/io/PrintStream;
      11: aload_1
      12: invokespecial #5                  // Method math:()I
      15: invokevirtual #6                  // Method java/io/PrintStream.println:(I)V
      18: getstatic     #4                  // Field java/lang/System.out:Ljava/io/PrintStream;
      21: ldc           #7                  // String end
      23: invokevirtual #8                  // Method java/io/PrintStream.println:(Ljava/lang/String;)V
      26: return

  static {};
    Code:
       0: sipush        666
       3: invokestatic  #9                  // Method java/lang/Integer.valueOf:(I)Ljava/lang/Integer;
       6: putstatic     #10                 // Field CONSTANT_1:Ljava/lang/Integer;
       9: return
}
