Compiled from "Demo.java"
public class com.czw.basic.Jvm.Demo {
  public com.czw.basic.Jvm.Demo();
    Code:
       0: aload_0
       1: invokespecial #1                  // Method java/lang/Object."<init>":()V
       4: return

  public static void main(java.String[]);
    Code:
       0: new           #2                  // class com/czw/basic/Jvm/Math
       3: dup
       4: invokespecial #3                  // Method com/czw/basic/Jvm/Math."<init>":()V
       7: astore_1
       8: getstatic     #4                  // Field java/lang/System.out:Ljava/io/PrintStream;
      11: aload_1
      12: invokevirtual #5                  // Method com/czw/basic/Jvm/Math.math:()I
      15: invokevirtual #6                  // Method java/io/PrintStream.println:(I)V
      18: getstatic     #4                  // Field java/lang/System.out:Ljava/io/PrintStream;
      21: ldc           #7                  // String hello World
      23: invokevirtual #8                  // Method java/io/PrintStream.println:(Ljava/lang/String;)V
      26: return
}
